silicron/__init__.py
silicron/api.py
silicron-0.0.4.dist-info/METADATA
silicron-0.0.4.dist-info/WHEEL
silicron-0.0.4.dist-info/top_level.txt
silicron-0.0.4.dist-info/RECORD
